{"cameraMode":{"drawMode":0,"name":"Shaded","section":"Shading Mode"},"sceneLighting":false,"audioPlay":false,"sceneViewState":{"m_AlwaysRefresh":false,"showFog":true,"showSkybox":false,"showFlares":true,"showImageEffects":true,"showParticleSystems":true,"showVisualEffectGraphs":true,"m_FxEnabled":true},"in2DMode":false,"pivot":{"x":-1.3382434844970704,"y":1.3204333782196046,"z":-1.046837329864502},"rotation":{"x":0.18023480474948884,"y":0.11071037501096726,"z":-0.020427478477358819,"w":0.9771737456321716},"size":1.5223520994186402,"orthographic":false}