{"cameraMode":{"drawMode":0,"name":"Shaded","section":"Shading Mode"},"sceneLighting":true,"audioPlay":false,"sceneViewState":{"m_AlwaysRefresh":false,"showFog":true,"showSkybox":true,"showFlares":true,"showImageEffects":true,"showParticleSystems":true,"showVisualEffectGraphs":true,"m_FxEnabled":false},"in2DMode":false,"pivot":{"x":173.2678680419922,"y":-264.30517578125,"z":-218.54171752929688},"rotation":{"x":0.07595793902873993,"y":0.9191436767578125,"z":-0.3182326555252075,"w":0.21938444674015046},"size":212.1320343017578,"orthographic":false}